odoo10_addon_pos_partner_firstname-10.0.1.0.1-nspkg.pth
odoo/addons/pos_partner_firstname/README.rst
odoo/addons/pos_partner_firstname/__init__.py
odoo/addons/pos_partner_firstname/__manifest__.py
odoo/addons/pos_partner_firstname/i18n/pos_partner_firstname.pot
odoo/addons/pos_partner_firstname/models/__init__.py
odoo/addons/pos_partner_firstname/models/res_partner.py
odoo/addons/pos_partner_firstname/readme/CONTRIBUTORS.rst
odoo/addons/pos_partner_firstname/readme/DESCRIPTION.rst
odoo/addons/pos_partner_firstname/static/description/icon.png
odoo/addons/pos_partner_firstname/static/description/index.html
odoo/addons/pos_partner_firstname/static/src/js/models.js
odoo/addons/pos_partner_firstname/static/src/js/screens.js
odoo/addons/pos_partner_firstname/static/src/xml/pos.xml
odoo/addons/pos_partner_firstname/views/assets.xml
odoo10_addon_pos_partner_firstname-10.0.1.0.1.dist-info/METADATA
odoo10_addon_pos_partner_firstname-10.0.1.0.1.dist-info/WHEEL
odoo10_addon_pos_partner_firstname-10.0.1.0.1.dist-info/namespace_packages.txt
odoo10_addon_pos_partner_firstname-10.0.1.0.1.dist-info/top_level.txt
odoo10_addon_pos_partner_firstname-10.0.1.0.1.dist-info/RECORD
